src/__init__.py
src/feature_engineering.py
forma_mlops-0.0.1.dist-info/METADATA
forma_mlops-0.0.1.dist-info/WHEEL
forma_mlops-0.0.1.dist-info/top_level.txt
forma_mlops-0.0.1.dist-info/RECORD
