Metadata-Version: 2.1
Name: forma-mlops
Version: 0.0.1
Summary: UNKNOWN
Home-page: UNKNOWN
Author: gireg.roussel
Author-email: 
License: UNKNOWN
Platform: UNKNOWN
Requires-Dist: numpy (<1.24,>=1.23)
Requires-Dist: pandas (==1.5.0)
